README.rst
setup.py
tinyapi/__init__.py
tinyapi/_version.py
tinyapi/draft.py
tinyapi/session.py
tinyapi.egg-info/PKG-INFO
tinyapi.egg-info/SOURCES.txt
tinyapi.egg-info/dependency_links.txt
tinyapi.egg-info/namespace_packages.txt
tinyapi.egg-info/not-zip-safe
tinyapi.egg-info/requires.txt
tinyapi.egg-info/top_level.txt