Metadata-Version: 1.1
Name: tinyapi
Version: 0.1.0
Summary: Python wrapper for TinyLetter's (publicly accessible, but undocumented) API.
Home-page: https://github.com/jsvine/tinyapi
Author: Jeremy Singer-Vine
Author-email: jsvine@gmail.com
License: MIT
Keywords: tinyletter api
Platform: UNKNOWN
Classifier: Programming Language :: Python :: 2
Classifier: Programming Language :: Python :: 2.7
Classifier: Programming Language :: Python :: 3
Classifier: Programming Language :: Python :: 3.1
Classifier: Programming Language :: Python :: 3.4
Classifier: Programming Language :: Python :: 3.5
Classifier: Intended Audience :: Developers
Classifier: License :: OSI Approved :: MIT License
